{
    "composer": "Mozart", 
    "discs": [
        {
            "label": "Track Listing - Disc 1", 
            "performances": [
                {
                    "label": "Concerto No. 1 in F major, K 37", 
                    "movements": [
                        {
                            "duration": 312, 
                            "durationR": "5:12", 
                            "label": "1. Allegro", 
                            "start": 0, 
                            "track": "1"
                        }, 
                        {
                            "duration": 311, 
                            "durationR": "5:11", 
                            "label": "2. Andante", 
                            "start": 312, 
                            "track": "2"
                        }, 
                        {
                            "duration": 291, 
                            "durationR": "4:51", 
                            "label": "3. Allegro", 
                            "start": 623, 
                            "track": "3"
                        }
                    ]
                }, 
                {
                    "label": "Concerto No. 2 in B flat major, K 39", 
                    "movements": [
                        {
                            "duration": 303, 
                            "durationR": "5:03", 
                            "label": "1. Allegro spiritoso", 
                            "start": 914, 
                            "track": "4"
                        }, 
                        {
                            "duration": 310, 
                            "durationR": "5:10", 
                            "label": "2. Andante", 
                            "start": 1217, 
                            "track": "5"
                        }, 
                        {
                            "duration": 263, 
                            "durationR": "4:23", 
                            "label": "3. Molto allegro", 
                            "start": 1527, 
                            "track": "6"
                        }
                    ]
                }, 
                {
                    "label": "Concerto No. 3 in D major, K 40", 
                    "movements": [
                        {
                            "duration": 318, 
                            "durationR": "5:18", 
                            "label": "1. Allegro maestoso", 
                            "start": 1790, 
                            "track": "7"
                        }, 
                        {
                            "duration": 273, 
                            "durationR": "4:33", 
                            "label": "2. Andante", 
                            "start": 2108, 
                            "track": "8"
                        }, 
                        {
                            "duration": 144, 
                            "durationR": "2:24", 
                            "label": "3. Presto", 
                            "start": 2381, 
                            "track": "9"
                        }
                    ]
                }, 
                {
                    "label": "Concerto No. 4 in G major, K 41", 
                    "movements": [
                        {
                            "duration": 302, 
                            "durationR": "5:02", 
                            "label": "1. Allegro", 
                            "start": 2525, 
                            "track": "10"
                        }, 
                        {
                            "duration": 281, 
                            "durationR": "4:41", 
                            "label": "2. Andante", 
                            "start": 2827, 
                            "track": "11"
                        }, 
                        {
                            "duration": 219, 
                            "durationR": "3:39", 
                            "label": "3. Molto allegro", 
                            "start": 3108, 
                            "track": "12"
                        }
                    ]
                }, 
                {
                    "label": "Concerto No. 5 in D major, K 175", 
                    "movements": [
                        {
                            "duration": 488, 
                            "durationR": "8:08", 
                            "label": "1. Allegro", 
                            "start": 3327, 
                            "track": "13"
                        }, 
                        {
                            "duration": 455, 
                            "durationR": "7:35", 
                            "label": "2. Andante ma un poco adagio", 
                            "start": 3815, 
                            "track": "14"
                        }, 
                        {
                            "duration": 293, 
                            "durationR": "4:53", 
                            "label": "3. Allegro", 
                            "start": 4270, 
                            "track": "15"
                        }
                    ]
                }
            ]
        }, 
        {
            "label": "Track Listing - Disc 2", 
            "performances": [
                {
                    "label": "Concerto No. 6 in B flat major, K 238", 
                    "movements": [
                        {
                            "duration": 407, 
                            "durationR": "6:47", 
                            "label": "1. Allegro aperto", 
                            "start": 0, 
                            "track": "1"
                        }, 
                        {
                            "duration": 361, 
                            "durationR": "6:01", 
                            "label": "2. Andante un poco adagio", 
                            "start": 407, 
                            "track": "2"
                        }, 
                        {
                            "duration": 452, 
                            "durationR": "7:32", 
                            "label": "3. Rondeau: Allegro", 
                            "start": 768, 
                            "track": "3"
                        }
                    ]
                }, 
                {
                    "label": "Concerto No. 8 in C major, K 246", 
                    "movements": [
                        {
                            "duration": 451, 
                            "durationR": "7:31", 
                            "label": "1. Allegro aperto", 
                            "start": 1220, 
                            "track": "4"
                        }, 
                        {
                            "duration": 476, 
                            "durationR": "7:56", 
                            "label": "2. Andante", 
                            "start": 1671, 
                            "track": "5"
                        }, 
                        {
                            "duration": 444, 
                            "durationR": "7:24", 
                            "label": "3. Rondeau: Tempo di menuetto", 
                            "start": 2147, 
                            "track": "6"
                        }
                    ]
                }, 
                {
                    "label": "Concerto No. 9 in E flat major, K 271", 
                    "movements": [
                        {
                            "duration": 628, 
                            "durationR": "10:28", 
                            "label": "1. Allegro", 
                            "start": 2591, 
                            "track": "7"
                        }, 
                        {
                            "duration": 746, 
                            "durationR": "12:26", 
                            "label": "2. Andantino", 
                            "start": 3219, 
                            "track": "8"
                        }, 
                        {
                            "duration": 634, 
                            "durationR": "10:34", 
                            "label": "3. Rondeau: Presto - Menuetto", 
                            "start": 3965, 
                            "track": "9"
                        }
                    ]
                }
            ]
        }, 
        {
            "label": "Track Listing - Disc 3", 
            "performances": [
                {
                    "label": "Concerto No. 7 in F major, for 3 pianos, K 242", 
                    "movements": [
                        {
                            "duration": 523, 
                            "durationR": "8:43", 
                            "label": "1. Allegro", 
                            "start": 0, 
                            "track": "1"
                        }, 
                        {
                            "duration": 521, 
                            "durationR": "8:41", 
                            "label": "2. Adagio", 
                            "start": 523, 
                            "track": "2"
                        }, 
                        {
                            "duration": 359, 
                            "durationR": "5:59", 
                            "label": "3. Rondeau: Tempo di minuetto", 
                            "start": 1044, 
                            "track": "3"
                        }
                    ]
                }, 
                {
                    "label": "Concerto No. 10 in E flat major, for 2 pianos, K 365", 
                    "movements": [
                        {
                            "duration": 617, 
                            "durationR": "10:17", 
                            "label": "1. Allegro", 
                            "start": 1403, 
                            "track": "4"
                        }, 
                        {
                            "duration": 480, 
                            "durationR": "8:00", 
                            "label": "2. Andante", 
                            "start": 2020, 
                            "track": "5"
                        }, 
                        {
                            "duration": 412, 
                            "durationR": "6:52", 
                            "label": "3. Rondeau: Allegro", 
                            "start": 2500, 
                            "track": "6"
                        }
                    ]
                }, 
                {
                    "label": "Concerto No. 11 in F major, K 413", 
                    "movements": [
                        {
                            "duration": 535, 
                            "durationR": "8:55", 
                            "label": "1. Allegro", 
                            "start": 2912, 
                            "track": "7"
                        }, 
                        {
                            "duration": 435, 
                            "durationR": "7:15", 
                            "label": "2. Larghetto", 
                            "start": 3447, 
                            "track": "8"
                        }, 
                        {
                            "duration": 318, 
                            "durationR": "5:18", 
                            "label": "3. Tempo di Menuetto", 
                            "start": 3882, 
                            "track": "9"
                        }
                    ]
                }
            ]
        }, 
        {
            "label": "Track Listing - Disc 4", 
            "performances": [
                {
                    "label": "Concerto No. 12 in A major, K 414", 
                    "movements": [
                        {
                            "duration": 643, 
                            "durationR": "10:43", 
                            "label": "1. Allegro", 
                            "start": 0, 
                            "track": "1"
                        }, 
                        {
                            "duration": 507, 
                            "durationR": "8:27", 
                            "label": "2. Andante", 
                            "start": 643, 
                            "track": "2"
                        }, 
                        {
                            "duration": 418, 
                            "durationR": "6:58", 
                            "label": "3. Rondeau: Allegretto", 
                            "start": 1150, 
                            "track": "3"
                        }
                    ]
                }, 
                {
                    "label": "Concerto No. 13 in C major, K 415", 
                    "movements": [
                        {
                            "duration": 634, 
                            "durationR": "10:34", 
                            "label": "1. Allegro", 
                            "start": 1568, 
                            "track": "4"
                        }, 
                        {
                            "duration": 425, 
                            "durationR": "7:05", 
                            "label": "2. Andante", 
                            "start": 2202, 
                            "track": "5"
                        }, 
                        {
                            "duration": 496, 
                            "durationR": "8:16", 
                            "label": "3. Rondeau: Allegro", 
                            "start": 2627, 
                            "track": "6"
                        }
                    ]
                }, 
                {
                    "label": "Concerto No. 14 in E flat major, K 449", 
                    "movements": [
                        {
                            "duration": 542, 
                            "durationR": "9:02", 
                            "label": "1. Allegro vivace", 
                            "start": 3123, 
                            "track": "7"
                        }, 
                        {
                            "duration": 402, 
                            "durationR": "6:42", 
                            "label": "2. Andantino", 
                            "start": 3665, 
                            "track": "8"
                        }, 
                        {
                            "duration": 393, 
                            "durationR": "6:33", 
                            "label": "3. Allegro ma non troppo", 
                            "start": 4067, 
                            "track": "9"
                        }
                    ]
                }
            ]
        }, 
        {
            "label": "Track Listing - Disc 5", 
            "performances": [
                {
                    "label": "Concerto No. 15 in B flat major, K 450", 
                    "movements": [
                        {
                            "duration": 626, 
                            "durationR": "10:26", 
                            "label": "1. Allegro", 
                            "start": 0, 
                            "track": "1"
                        }, 
                        {
                            "duration": 347, 
                            "durationR": "5:47", 
                            "label": "2. Andante", 
                            "start": 626, 
                            "track": "2"
                        }, 
                        {
                            "duration": 463, 
                            "durationR": "7:43", 
                            "label": "3. Allegro", 
                            "start": 973, 
                            "track": "3"
                        }
                    ]
                }, 
                {
                    "label": "Concerto No. 16 in D major, K 451", 
                    "movements": [
                        {
                            "duration": 633, 
                            "durationR": "10:33", 
                            "label": "1. Allegro assai", 
                            "start": 1436, 
                            "track": "4"
                        }, 
                        {
                            "duration": 293, 
                            "durationR": "4:53", 
                            "label": "2. Andante", 
                            "start": 2069, 
                            "track": "5"
                        }, 
                        {
                            "duration": 391, 
                            "durationR": "6:31", 
                            "label": "3. Rondeau: Allegro di molto", 
                            "start": 2362, 
                            "track": "6"
                        }
                    ]
                }, 
                {
                    "label": "Concerto No. 17 in G major, K 453", 
                    "movements": [
                        {
                            "duration": 716, 
                            "durationR": "11:56", 
                            "label": "1. Allegro", 
                            "start": 2753, 
                            "track": "7"
                        }, 
                        {
                            "duration": 667, 
                            "durationR": "11:07", 
                            "label": "2. Andante", 
                            "start": 3469, 
                            "track": "8"
                        }, 
                        {
                            "duration": 451, 
                            "durationR": "7:31", 
                            "label": "3. Allegretto - Finale: Presto", 
                            "start": 4136, 
                            "track": "9"
                        }
                    ]
                }
            ]
        }, 
        {
            "label": "Track Listing - Disc 6", 
            "performances": [
                {
                    "label": "Concerto No. 18 in B flat major, K 456", 
                    "movements": [
                        {
                            "duration": 728, 
                            "durationR": "12:08", 
                            "label": "1. Allegro vivace", 
                            "start": 0, 
                            "track": "1"
                        }, 
                        {
                            "duration": 561, 
                            "durationR": "9:21", 
                            "label": "2. Andante un poco sostenuto", 
                            "start": 728, 
                            "track": "2"
                        }, 
                        {
                            "duration": 469, 
                            "durationR": "7:49", 
                            "label": "3. Allegro vivace", 
                            "start": 1289, 
                            "track": "3"
                        }
                    ]
                }, 
                {
                    "label": "Concerto No. 19 in F major, K 459", 
                    "movements": [
                        {
                            "duration": 704, 
                            "durationR": "11:44", 
                            "label": "1. Allegro", 
                            "start": 1758, 
                            "track": "4"
                        }, 
                        {
                            "duration": 482, 
                            "durationR": "8:02", 
                            "label": "2. Allegretto", 
                            "start": 2462, 
                            "track": "5"
                        }, 
                        {
                            "duration": 456, 
                            "durationR": "7:36", 
                            "label": "3. Allegro assai", 
                            "start": 2944, 
                            "track": "6"
                        }, 
                        {
                            "duration": 608, 
                            "durationR": "10:08", 
                            "label": "Rondo in D major, K 382", 
                            "start": 3400, 
                            "track": "7"
                        }
                    ]
                }
            ]
        }, 
        {
            "label": "Track Listing - Disc 7", 
            "performances": [
                {
                    "label": "Concerto No. 20 in D minor, K 466", 
                    "movements": [
                        {
                            "duration": 813, 
                            "durationR": "13:33", 
                            "label": "1. Allegro", 
                            "start": 0, 
                            "track": "1"
                        }, 
                        {
                            "duration": 525, 
                            "durationR": "8:45", 
                            "label": "2. Romance", 
                            "start": 813, 
                            "track": "2"
                        }, 
                        {
                            "duration": 432, 
                            "durationR": "7:12", 
                            "label": "3. Allegro assai", 
                            "start": 1338, 
                            "track": "3"
                        }
                    ]
                }, 
                {
                    "label": "Concerto No. 21 in C major, K 467", 
                    "movements": [
                        {
                            "duration": 857, 
                            "durationR": "14:17", 
                            "label": "1. (Allegro maestoso)", 
                            "start": 1770, 
                            "track": "4"
                        }, 
                        {
                            "duration": 503, 
                            "durationR": "8:23", 
                            "label": "2. Andante", 
                            "start": 2627, 
                            "track": "5"
                        }, 
                        {
                            "duration": 452, 
                            "durationR": "7:32", 
                            "label": "3. Allegro vivace assai", 
                            "start": 3130, 
                            "track": "6"
                        }, 
                        {
                            "duration": 513, 
                            "durationR": "8:33", 
                            "label": "Rondo in A major, K 386", 
                            "start": 3582, 
                            "track": "7"
                        }
                    ]
                }
            ]
        }, 
        {
            "label": "Track Listing - Disc 8", 
            "performances": [
                {
                    "label": "Concerto No. 22 in E flat major, K 482", 
                    "movements": [
                        {
                            "duration": 815, 
                            "durationR": "13:35", 
                            "label": "1. Allegro", 
                            "start": 0, 
                            "track": "1"
                        }, 
                        {
                            "duration": 590, 
                            "durationR": "9:50", 
                            "label": "2. Andante", 
                            "start": 815, 
                            "track": "2"
                        }, 
                        {
                            "duration": 731, 
                            "durationR": "12:11", 
                            "label": "3. Allegro - Andantino cantabile - Primo tempo", 
                            "start": 1405, 
                            "track": "3"
                        }
                    ]
                }, 
                {
                    "label": "Concerto No. 23 in A major, K 488", 
                    "movements": [
                        {
                            "duration": 703, 
                            "durationR": "11:43", 
                            "label": "1. Allegro", 
                            "start": 2136, 
                            "track": "4"
                        }, 
                        {
                            "duration": 384, 
                            "durationR": "6:24", 
                            "label": "2. Adagio", 
                            "start": 2839, 
                            "track": "5"
                        }, 
                        {
                            "duration": 482, 
                            "durationR": "8:02", 
                            "label": "3. Allegro assai", 
                            "start": 3223, 
                            "track": "6"
                        }, 
                        {
                            "duration": 555, 
                            "durationR": "9:15", 
                            "label": "Rondo in A minor, for solo piano, K 511", 
                            "start": 3705, 
                            "track": "7"
                        }
                    ]
                }
            ]
        }, 
        {
            "label": "Track Listing - Disc 9", 
            "performances": [
                {
                    "label": "Concerto No. 24 in C minor, K 491", 
                    "movements": [
                        {
                            "duration": 846, 
                            "durationR": "14:06", 
                            "label": "1. Allegro", 
                            "start": 0, 
                            "track": "1"
                        }, 
                        {
                            "duration": 491, 
                            "durationR": "8:11", 
                            "label": "2. Larghetto", 
                            "start": 846, 
                            "track": "2"
                        }, 
                        {
                            "duration": 578, 
                            "durationR": "9:38", 
                            "label": "3. Allegretto", 
                            "start": 1337, 
                            "track": "3"
                        }
                    ]
                }, 
                {
                    "label": "Concerto No. 25 in C major, K 503", 
                    "movements": [
                        {
                            "duration": 819, 
                            "durationR": "13:39", 
                            "label": "1. Allegro maestoso", 
                            "start": 1915, 
                            "track": "4"
                        }, 
                        {
                            "duration": 461, 
                            "durationR": "7:41", 
                            "label": "2. Andante", 
                            "start": 2734, 
                            "track": "5"
                        }, 
                        {
                            "duration": 553, 
                            "durationR": "9:13", 
                            "label": "3. Allegretto", 
                            "start": 3195, 
                            "track": "6"
                        }
                    ]
                }
            ]
        }, 
        {
            "label": "Track Listing - Disc 10", 
            "performances": [
                {
                    "label": "Concerto No. 26 in D major, K 537 'Coronation'", 
                    "movements": [
                        {
                            "duration": 916, 
                            "durationR": "15:16", 
                            "label": "1. Allegro", 
                            "start": 0, 
                            "track": "1"
                        }, 
                        {
                            "duration": 389, 
                            "durationR": "6:29", 
                            "label": "2. Larghetto", 
                            "start": 916, 
                            "track": "2"
                        }, 
                        {
                            "duration": 684, 
                            "durationR": "11:24", 
                            "label": "3. Allegretto", 
                            "start": 1305, 
                            "track": "3"
                        }
                    ]
                }, 
                {
                    "label": "Concerto No. 27 in B flat major, K 595", 
                    "movements": [
                        {
                            "duration": 842, 
                            "durationR": "14:02", 
                            "label": "1. Allegro", 
                            "start": 1989, 
                            "track": "4"
                        }, 
                        {
                            "duration": 484, 
                            "durationR": "8:04", 
                            "label": "2. Larghetto", 
                            "start": 2831, 
                            "track": "5"
                        }, 
                        {
                            "duration": 552, 
                            "durationR": "9:12", 
                            "label": "3. Allegro", 
                            "start": 3315, 
                            "track": "6"
                        }
                    ]
                }
            ]
        }
    ], 
    "label": "Piano Concerto"
}
